{
  "run_id": "smoke-local",
  "project": "hex6",
  "phase": "fast_sprint",
  "config_path": "configs/fast.toml",
  "output_dir": "artifacts/bootstrap_status_smoke",
  "status_backend": "github_branch",
  "host": "DESKTOP-FDD9NTI",
  "started_at": "2026-03-07T21:29:13Z",
  "updated_at": "2026-03-07T21:29:47Z",
  "sequence": 5,
  "stage": "complete",
  "device": "cuda",
  "examples": 5,
  "encoded_examples": 4,
  "epochs": 1,
  "final_policy_loss": 5.5087890625,
  "final_value_loss": 0.08823993802070618,
  "checkpoint": "artifacts\\bootstrap_status_smoke\\bootstrap_model.pt"
}